langchain_goodfire/__init__.py
langchain_goodfire/chat_model.py
langchain_goodfire-0.2.4.dist-info/METADATA
langchain_goodfire-0.2.4.dist-info/WHEEL
langchain_goodfire-0.2.4.dist-info/licenses/LICENSE
langchain_goodfire-0.2.4.dist-info/RECORD
