Metadata-Version: 2.4
Name: langchain-goodfire
Version: 0.2.4
Summary: Goodfire integration for LangChain
Project-URL: Homepage, https://github.com/keenanpepper/langchain-goodfire
Project-URL: Bug Tracker, https://github.com/keenanpepper/langchain-goodfire/issues
Author-email: Keenan Pepper <keenan@ae.studio>
License-File: LICENSE
Classifier: License :: OSI Approved :: MIT License
Classifier: Operating System :: OS Independent
Classifier: Programming Language :: Python :: 3
Requires-Python: >=3.8.1
Requires-Dist: goodfire>=0.3.4
Requires-Dist: jinja2>=3.1.5
Requires-Dist: langchain-core>=0.3.32
Requires-Dist: transformers>=4.48.1
Provides-Extra: dev
Requires-Dist: langchain-tests==0.3.10; extra == 'dev'
Requires-Dist: pytest>=7.0.0; extra == 'dev'
Requires-Dist: python-dotenv; extra == 'dev'
